pyhtools/UI/__init__.py
pyhtools/UI/colors.py
pyhtools/UI/functions.py
pyhtools/__init__.py
pyhtools/__main__.py
pyhtools/attackers/Android/__init__.py
pyhtools/attackers/Android/forensics/__init__.py
pyhtools/attackers/Android/forensics/data_harvester.py
pyhtools/attackers/Android/mitm/__init__.py
pyhtools/attackers/Android/mitm/cert_pin.py
pyhtools/attackers/Android/mitm/utils.py
pyhtools/attackers/Network/__init__.py
pyhtools/attackers/Network/arpspoofer.py
pyhtools/attackers/Network/code_injector.py
pyhtools/attackers/Network/dnsspoofer.py
pyhtools/attackers/Network/downloads_replacer.py
pyhtools/attackers/Network/machngr.py
pyhtools/attackers/Network/network_jammer.py
pyhtools/attackers/Network/nwscan.py
pyhtools/attackers/Network/pkt_sniffer.py
pyhtools/attackers/Network/tcp_proxy.py
pyhtools/attackers/__init__.py
pyhtools/attackers/attackers.py
pyhtools/attackers/web/__init__.py
pyhtools/attackers/web/api/__init__.py
pyhtools/attackers/web/api/discover.py
pyhtools/attackers/web/enumerate.py
pyhtools/attackers/web/get_forms.py
pyhtools/attackers/web/login_guesser.py
pyhtools/attackers/web/spider.py
pyhtools/attackers/web/utils.py
pyhtools/attackers/web/vuln_scanner/__init__.py
pyhtools/attackers/web/vuln_scanner/__main__.py
pyhtools/attackers/web/vuln_scanner/scanner.py
pyhtools/attackers/web/vuln_scanner/sqli.py
pyhtools/detectors/__init__.py
pyhtools/detectors/arp_spoof_detector.py
pyhtools/detectors/win_block_usb.py
pyhtools/utils.py
pyhtools-2.3.4.dist-info/LICENSE
pyhtools-2.3.4.dist-info/METADATA
pyhtools-2.3.4.dist-info/WHEEL
pyhtools-2.3.4.dist-info/entry_points.txt
pyhtools-2.3.4.dist-info/RECORD
