Metadata-Version: 2.1
Name: pyhtools
Version: 2.3.4
Summary: Python Hacking Tools (PyHTools) (pht) is a collection of python written hacking tools consisting of network scanner, arp spoofer and detector, dns spoofer, code injector, packet sniffer, network jammer, email sender, downloader, wireless password harvester credential harvester, keylogger, download&execute, and reverse_backdoor along with website login bruteforce, scraper, web spider etc. PHT also includes malwares which are undetectable by the antiviruses.
License: MIT
Author: Dhrumil Mistry
Author-email: contact@dmdhrumilmistry.tech
Requires-Python: >=3.8,<4.0
Classifier: License :: OSI Approved :: MIT License
Classifier: Programming Language :: Python :: 3
Classifier: Programming Language :: Python :: 3.8
Classifier: Programming Language :: Python :: 3.9
Classifier: Programming Language :: Python :: 3.10
Classifier: Programming Language :: Python :: 3.11
Classifier: Programming Language :: Python :: 3.12
Provides-Extra: dev
Provides-Extra: docs
Provides-Extra: linux
Provides-Extra: windows
Requires-Dist: aiodns (>=3.0.0,<4.0.0)
Requires-Dist: aiohttp (>=3.8.4,<4.0.0)
Requires-Dist: beautifulsoup4 (>=4.11.2,<5.0.0)
Requires-Dist: colorama (>=0.4.6,<0.5.0)
Requires-Dist: frida-tools (>=12.2.1,<13.0.0)
Requires-Dist: mkdocs (>=1.4.3,<2.0.0) ; extra == "docs"
Requires-Dist: mkdocs-material (>=9.1.12,<10.0.0) ; extra == "docs"
Requires-Dist: mkdocstrings[python] (>=0.21.2,<0.22.0) ; extra == "docs"
Requires-Dist: netfilterqueue (>=1.1.0,<2.0.0) ; extra == "linux"
Requires-Dist: packaging (>=23.1,<24.0) ; extra == "dev"
Requires-Dist: paramiko (>=3.0.0,<4.0.0)
Requires-Dist: prettytable (>=3.6.0,<4.0.0)
Requires-Dist: psutil (>=5.9.4,<6.0.0)
Requires-Dist: pure-python-adb (==0.3.*)
Requires-Dist: pyfiglet (>=0.8.post1,<0.9)
Requires-Dist: pynput (>=1.7.6,<2.0.0)
Requires-Dist: requests (>=2.28.2,<3.0.0)
Requires-Dist: scapy (>=2.5.0,<3.0.0)
Requires-Dist: wmi (>=1.5.1,<2.0.0) ; extra == "windows"
Requires-Dist: zstandard (>=0.20.0,<0.21.0)
Project-URL: Bug Tracker, https://github.com/dmdhrumilmistry/pyhtools/issues
Project-URL: Home, https://github.com/dmdhrumilmistry/pyhtools
Project-URL: PayPal, https://paypal.me/dmdhrumilmistry
Project-URL: Support, https://github.com/sponsors/dmdhrumilmistry/
